freenom/__init__.py
freenom-0.0.2.dist-info/LICENSE
freenom-0.0.2.dist-info/METADATA
freenom-0.0.2.dist-info/WHEEL
freenom-0.0.2.dist-info/top_level.txt
freenom-0.0.2.dist-info/RECORD
