Metadata-Version: 2.1
Name: freenom
Version: 0.0.2
Summary: Freenom DNS API
Home-page: https://github.com/Shm013/freenom-dns
Author: Nikolay Shamanovich
Author-email: shm013@yandex.ru
License: UNKNOWN
Platform: UNKNOWN
Classifier: Programming Language :: Python :: 3
Classifier: License :: OSI Approved :: MIT License
Classifier: Operating System :: OS Independent
Requires-Python: >=3.6
Requires-Dist: requests (>=2.23.0)
Requires-Dist: lxml (>=4.5.0)
Requires-Dist: retrying (>=1.3.3)
